MANIFEST.in
README.md
setup.cfg
setup.py
main/BDCA.py
main/BDres.py
main/Comprobaciones.py
main/GestionClientes.py
main/GestionFacturas.py
main/GestionMesas.py
main/GestionProd.py
main/Main.py
main/__init__.py
main/sacarpdf.py
restaurante_daviddss.egg-info/PKG-INFO
restaurante_daviddss.egg-info/SOURCES.txt
restaurante_daviddss.egg-info/dependency_links.txt
restaurante_daviddss.egg-info/top_level.txt