Metadata-Version: 2.1
Name: restaurante-daviddss
Version: 0.0.7
Summary: Un gestor para un restaurante
Home-page: UNKNOWN
Author: David da Silva
Author-email: davdes15@gmail.com
License: UNKNOWN
Platform: UNKNOWN
Classifier: Programming Language :: Python :: 3
Classifier: License :: OSI Approved :: MIT License
Classifier: Operating System :: OS Independent
